certs/CA.crt
certs/CA.key
certs/CA.p12
certs/README.md
certs/ca-bundle.crt
certs/client.crt
certs/client.key
certs/localhost.crt
certs/localhost.csr
certs/localhost.key
certs/localhost.p12
koi/__init__.py
koi/auth.py
koi/base.py
koi/commands.py
koi/configure.py
koi/constants.py
koi/exceptions.py
koi/keygen.py
koi/test_helpers.py
koi/utils.py
opp_koi-1.1.0.dist-info/DESCRIPTION.rst
opp_koi-1.1.0.dist-info/METADATA
opp_koi-1.1.0.dist-info/RECORD
opp_koi-1.1.0.dist-info/WHEEL
opp_koi-1.1.0.dist-info/metadata.json
opp_koi-1.1.0.dist-info/top_level.txt
