Metadata-Version: 2.0
Name: opp-koi
Version: 1.1.0
Summary: Helpers and utilities shared by OPP tornado applications
Home-page: https://github.com/openpermissions/koi
Author: Open Permissions Platform Coalition
Author-email: support@openpermissions.org
License: Apache 2.0
Platform: UNKNOWN
Requires-Dist: click
Requires-Dist: opp-chub (>=1.0.5)
Requires-Dist: tornado (>=4.2.0)
